[
  {
    "slug": "aishah-sofey",
    "file": "aishah-sofey.webp"
  },
  {
    "slug": "alice-rosenblum",
    "file": "alice-rosenblum.webp"
  },
  {
    "slug": "alinaxrose",
    "file": "alinaxrose.webp"
  },
  {
    "slug": "amber-ajami",
    "file": "amber-ajami.webp"
  },
  {
    "slug": "amouranth",
    "file": "amouranth.webp"
  },
  {
    "slug": "ari-kytsya",
    "file": "ari-kytsya.webp"
  },
  {
    "slug": "belle-delphine",
    "file": "belle-delphine.webp"
  },
  {
    "slug": "bhad-bhabie",
    "file": "bhad-bhabie.webp"
  },
  {
    "slug": "breckie-hill",
    "file": "breckie-hill.webp"
  },
  {
    "slug": "bunni-emmie",
    "file": "bunni-emmie.webp"
  },
  {
    "slug": "camilla-araujo",
    "file": "camilla-araujo.webp"
  },
  {
    "slug": "corinna-kopf",
    "file": "corinna-kopf.webp"
  },
  {
    "slug": "jameliz",
    "file": "jameliz.webp"
  },
  {
    "slug": "julia-filippo",
    "file": "julia-filippo.webp"
  },
  {
    "slug": "katiana-kay",
    "file": "katiana-kay.webp"
  },
  {
    "slug": "kira-pregiato",
    "file": "kira-pregiato.webp"
  },
  {
    "slug": "lela-sohna",
    "file": "lela-sohna.webp"
  },
  {
    "slug": "lil-tay",
    "file": "lil-tay.webp"
  },
  {
    "slug": "mia-khalifa",
    "file": "mia-khalifa.webp"
  },
  {
    "slug": "piper-rockelle",
    "file": "piper-rockelle.webp"
  },
  {
    "slug": "sophie-rain",
    "file": "sophie-rain.webp"
  },
  {
    "slug": "summerxiris",
    "file": "summerxiris.webp"
  },
  {
    "slug": "tana-mongeau",
    "file": "tana-mongeau.webp"
  },
  {
    "slug": "vera-dijkmans",
    "file": "vera-dijkmans.webp"
  },
  {
    "slug": "waifumia",
    "file": "waifumia.webp"
  }
]